{
  "version": "5.0",
  "last_updated": "2026-05-15 14:16:56",
  "total_closed_trades": 90,
  "total_wins": 37,
  "total_losses": 53,
  "global": {
    "trades": 90.0,
    "wins": 37.0,
    "losses": 53.0,
    "win_rate": 0.4111,
    "posterior_win_rate": 0.4149,
    "sample_confidence": 1.0,
    "family_quality_score": 41.49,
    "weight": 0.966,
    "memory_active": true
  },
  "families": {
    "GENERAL": {
      "trades": 49.5598,
      "wins": 20.0014,
      "losses": 29.5584,
      "win_rate": 0.4036,
      "posterior_win_rate": 0.4108,
      "sample_confidence": 1.0,
      "family_quality_score": 41.08,
      "weight": 0.9643,
      "memory_active": true
    }
  },
  "symbols": {
    "TATASTEEL": {
      "trades": 1.544,
      "wins": 0.559,
      "losses": 0.985,
      "win_rate": 0.362,
      "posterior_win_rate": 0.4616,
      "sample_confidence": 0.0515,
      "family_quality_score": 49.8,
      "weight": 0.9992,
      "memory_active": false
    },
    "TCS": {
      "trades": 3.8532,
      "wins": 2.83,
      "losses": 1.0232,
      "win_rate": 0.7345,
      "posterior_win_rate": 0.615,
      "sample_confidence": 0.1284,
      "family_quality_score": 51.48,
      "weight": 1.0059,
      "memory_active": false
    },
    "M&M": {
      "trades": 1.2825,
      "wins": 0.5761,
      "losses": 0.7064,
      "win_rate": 0.4492,
      "posterior_win_rate": 0.4877,
      "sample_confidence": 0.0428,
      "family_quality_score": 49.95,
      "weight": 0.9998,
      "memory_active": false
    },
    "BAJAJ-AUTO": {
      "trades": 4.7008,
      "wins": 0.0,
      "losses": 4.7008,
      "win_rate": 0.0,
      "posterior_win_rate": 0.2299,
      "sample_confidence": 0.1567,
      "family_quality_score": 45.77,
      "weight": 0.9831,
      "memory_active": false
    },
    "RELIANCE": {
      "trades": 2.1738,
      "wins": 1.2181,
      "losses": 0.9557,
      "win_rate": 0.5604,
      "posterior_win_rate": 0.5213,
      "sample_confidence": 0.0725,
      "family_quality_score": 50.15,
      "weight": 1.0006,
      "memory_active": false
    },
    "PFC": {
      "trades": 5.0875,
      "wins": 0.281,
      "losses": 4.8066,
      "win_rate": 0.0552,
      "posterior_win_rate": 0.251,
      "sample_confidence": 0.1696,
      "family_quality_score": 45.78,
      "weight": 0.9831,
      "memory_active": true
    },
    "ULTRACEMCO": {
      "trades": 0.2852,
      "wins": 0.0,
      "losses": 0.2852,
      "win_rate": 0.0,
      "posterior_win_rate": 0.4667,
      "sample_confidence": 0.0095,
      "family_quality_score": 49.97,
      "weight": 0.9999,
      "memory_active": false
    },
    "JSWSTEEL": {
      "trades": 0.2896,
      "wins": 0.0,
      "losses": 0.2896,
      "win_rate": 0.0,
      "posterior_win_rate": 0.4662,
      "sample_confidence": 0.0097,
      "family_quality_score": 49.97,
      "weight": 0.9999,
      "memory_active": false
    },
    "BRITANNIA": {
      "trades": 0.294,
      "wins": 0.294,
      "losses": 0.0,
      "win_rate": 1.0,
      "posterior_win_rate": 0.5342,
      "sample_confidence": 0.0098,
      "family_quality_score": 50.03,
      "weight": 1.0001,
      "memory_active": false
    },
    "TECHM": {
      "trades": 1.5548,
      "wins": 0.3123,
      "losses": 1.2425,
      "win_rate": 0.2009,
      "posterior_win_rate": 0.4163,
      "sample_confidence": 0.0518,
      "family_quality_score": 49.57,
      "weight": 0.9983,
      "memory_active": false
    },
    "BHARTIARTL": {
      "trades": 5.5553,
      "wins": 4.834,
      "losses": 0.7213,
      "win_rate": 0.8702,
      "posterior_win_rate": 0.7152,
      "sample_confidence": 0.1852,
      "family_quality_score": 53.99,
      "weight": 1.0159,
      "memory_active": true
    },
    "HEROMOTOCO": {
      "trades": 7.345,
      "wins": 1.7908,
      "losses": 5.5542,
      "win_rate": 0.2438,
      "posterior_win_rate": 0.3341,
      "sample_confidence": 0.2448,
      "family_quality_score": 45.94,
      "weight": 0.9838,
      "memory_active": true
    },
    "ONGC": {
      "trades": 3.1654,
      "wins": 3.1654,
      "losses": 0.0,
      "win_rate": 1.0,
      "posterior_win_rate": 0.7209,
      "sample_confidence": 0.1055,
      "family_quality_score": 52.33,
      "weight": 1.0093,
      "memory_active": false
    },
    "AXISBANK": {
      "trades": 3.6811,
      "wins": 3.3066,
      "losses": 0.3744,
      "win_rate": 0.8983,
      "posterior_win_rate": 0.6909,
      "sample_confidence": 0.1227,
      "family_quality_score": 52.34,
      "weight": 1.0094,
      "memory_active": false
    },
    "TITAN": {
      "trades": 3.1611,
      "wins": 0.8341,
      "losses": 2.327,
      "win_rate": 0.2639,
      "posterior_win_rate": 0.3958,
      "sample_confidence": 0.1054,
      "family_quality_score": 48.9,
      "weight": 0.9956,
      "memory_active": false
    },
    "INFY": {
      "trades": 5.5867,
      "wins": 0.0,
      "losses": 5.5867,
      "win_rate": 0.0,
      "posterior_win_rate": 0.2086,
      "sample_confidence": 0.1862,
      "family_quality_score": 44.57,
      "weight": 0.9783,
      "memory_active": true
    }
  },
  "regimes": {
    "UNKNOWN": {
      "trades": 44.7076,
      "wins": 17.0898,
      "losses": 27.6178,
      "win_rate": 0.3823,
      "posterior_win_rate": 0.3919,
      "sample_confidence": 1.0,
      "family_quality_score": 39.19,
      "weight": 0.9568,
      "memory_active": true
    },
    "{\"market_ok\": true, \"reason\": \"Phase 4 data advantage market filter active\", \"di": {
      "trades": 4.8522,
      "wins": 2.9116,
      "losses": 1.9407,
      "win_rate": 0.6,
      "posterior_win_rate": 0.5548,
      "sample_confidence": 0.1617,
      "family_quality_score": 50.89,
      "weight": 1.0035,
      "memory_active": false
    }
  },
  "overfitting_controls": {
    "minimum_global_trades": 10,
    "minimum_family_trades": 5,
    "decay_factor": 0.985,
    "bayesian_prior": {
      "alpha": 2.0,
      "beta": 2.0
    },
    "family_quality_score_cap": [
      35.0,
      65.0
    ],
    "runtime_adjustment_cap": [
      -0.3,
      0.2
    ]
  }
}